[
  {
    "id": 0,
    "position": {
      "x": -1774.62,
      "y": -514.497986,
      "z": 10.1449966
    },
    "orientation": {
      "i": 0,
      "j": 0,
      "k": 0.707106769,
      "r": 0.707106769
    }
  },
  {
    "id": 1,
    "position": {
      "x": -1773.60596,
      "y": -517.876587,
      "z": 10.1449966
    },
    "orientation": {
      "i": 0,
      "j": 0,
      "k": 0.923879683,
      "r": 0.382683337
    }
  },
  {
    "id": 2,
    "position": {
      "x": -1770.69788,
      "y": -518.998413,
      "z": 10.1449966
    },
    "orientation": {
      "i": 0,
      "j": 0,
      "k": 1,
      "r": -0.0000001
    }
  },
  {
    "id": 3,
    "position": {
      "x": -1767.75085,
      "y": -517.892578,
      "z": 10.1449966
    },
    "orientation": {
      "i": 0,
      "j": 0,
      "k": 0.923879564,
      "r": -0.382683486
    }
  },
  {
    "id": 4,
    "position": {
      "x": -1766.56689,
      "y": -514.848572,
      "z": 10.1449966
    },
    "orientation": {
      "i": 0,
      "j": 0,
      "k": 0.707106709,
      "r": -0.707106829
    }
  },
  {
    "id": 5,
    "position": {
      "x": -1766.9585,
      "y": -511.597107,
      "z": 10.1449966
    },
    "orientation": {
      "i": 0,
      "j": 0,
      "k": 0.382683516,
      "r": -0.923879564
    }
  },
  {
    "id": 6,
    "position": {
      "x": -1772.93726,
      "y": -511.451782,
      "z": 10.1449966
    },
    "orientation": {
      "i": 0,
      "j": 0,
      "k": 0.382683486,
      "r": 0.923879564
    }
  },
  {
    "id": 7,
    "position": {
      "x": -1769.69128,
      "y": -510.111786,
      "z": 10.1449966
    },
    "orientation": {
      "i": 0,
      "j": 0,
      "k": 0,
      "r": 1
    }
  }
]

